{ "title": "\uD83D\uDE18 Naomivelvetxx’s Top Lovers \uD83D\uDE18",
  "contents":[
    {
      "name" : "Notice",
      "amount":"1. joe10ms (6200 tks)"
    },
    {
      "name" : "Notice",
      "amount":"2. rao00u3798 (5170 tks)"
    },
    {
      "name" : "Notice",
      "amount":"3. zzthabear (3911 tks)"
    },
    {
      "name" : "Notice",
      "amount":"And 720 more Lovers."
    },
    {
      "name" : "Notice",
      "amount":"\uD83D\uDC51 High Tip: joe10ms (2222 tks)"
    },
    {
      "name" : "Notice",
      "amount":"\uD83D\uDCCB Type /lovers any time to see the full board!"
    }
  ]
}